preconvert/__init__.py
preconvert/convert.py
preconvert/converters.py
preconvert/exceptions.py
preconvert/register.py
preconvert/output/__init__.py
preconvert/output/bson.py
preconvert/output/json.py
preconvert/output/msgpack.py
preconvert/output/simplejson.py
preconvert-0.0.6.dist-info/LICENSE
preconvert-0.0.6.dist-info/WHEEL
preconvert-0.0.6.dist-info/METADATA
preconvert-0.0.6.dist-info/RECORD
