Metadata-Version: 2.1
Name: preconvert
Version: 0.0.6
Summary: A Library to enable preconversion of any Python type into one that is easily serializable
Home-page: https://github.com/timothycrosley/preconvert
License: UNKNOWN
Author: Timothy Edmund Crosley
Author-email: timothy.crosley@gmail.com
Requires-Python: >=3.5
Classifier: Intended Audience :: Developers
Classifier: License :: OSI Approved :: MIT License
Classifier: Programming Language :: Python :: 3
Classifier: Topic :: Software Development :: Libraries :: Python Modules
Requires-Dist: pymongo; extra == "bson"
Requires-Dist: msgpack; extra == "msgpack"
Requires-Dist: simplejson; extra == "simplejson"
Provides-Extra: bson
Provides-Extra: msgpack
Provides-Extra: simplejson
